shapestats
