Metadata-Version: 1.2
Name: shapestats
Version: 0.2
Summary: tools & methods to measure shape regularity
Home-page: https://github.com/ljwolf/shapestats
Maintainer: Levi John Wolf
Maintainer-email: levi.john.wolf@gmail.com
License: MIT
Keywords: spatial statistics
Platform: UNKNOWN
Classifier: Intended Audience :: Science/Research
Classifier: Intended Audience :: Developers
Classifier: Intended Audience :: Education
Classifier: Topic :: Scientific/Engineering
Classifier: Topic :: Scientific/Engineering :: GIS
Classifier: License :: OSI Approved :: BSD License
Classifier: Programming Language :: Python
Classifier: Programming Language :: Python :: 3.5
Classifier: Programming Language :: Python :: 3.6
